yandex_summary/__init__.py
yandex_summary/api.py
yandex_summary-0.1.1.dist-info/METADATA
yandex_summary-0.1.1.dist-info/WHEEL
yandex_summary-0.1.1.dist-info/licenses/LICENSE
yandex_summary-0.1.1.dist-info/RECORD
