Metadata-Version: 2.4
Name: yandex_summary
Version: 0.1.1
Summary: Asynchronous YandexGPT summary API client
Author-email: Herman Guilliman <hermanguilliman@proton.me>
License-File: LICENSE
Requires-Python: >=3.13
Requires-Dist: aiohttp>=3.12.13
Requires-Dist: bs4>=0.0.2
